lb_dev/__init__.py
lb_dev/cli_commands.py
lb_dev/commands/__init__.py
lb_dev/commands/default_lb_dev.py
lb_dev/commands/copyright/__init__.py
lb_dev/commands/copyright/setup.py
lb_dev/commands/copyright/add_copyright_comment/__init__.py
lb_dev/commands/copyright/add_copyright_comment/add_copyright_comment.py
lb_dev/commands/copyright/builders/__init__.py
lb_dev/commands/copyright/builders/copyright_builder.py
lb_dev/commands/copyright/check_copyright_comment/__init__.py
lb_dev/commands/copyright/check_copyright_comment/check_copyright_comment.py
lb_dev/commands/copyright/check_for_license_file/__init__.py
lb_dev/commands/copyright/check_for_license_file/check_for_license.py
lb_dev/commands/copyright/create_license_file/__init__.py
lb_dev/commands/copyright/create_license_file/create_license_file.py
lb_dev/commands/copyright/scanner/__init__.py
lb_dev/commands/copyright/scanner/copyright_scanner.py
lb_dev/constants/__init__.py
lb_dev/constants/lb_dev_constants.py
lb_dev/constants/license_constants.py
lb_dev/data/__init__.py
lb_dev/data/default.clang-format
lb_dev/hooks/__init__.py
lb_dev/hooks/check_copyright_comments_hook.py
lb_dev/hooks/check_license_hook.py
lb_dev-0.0.5.dist-info/LICENSE
lb_dev-0.0.5.dist-info/METADATA
lb_dev-0.0.5.dist-info/WHEEL
lb_dev-0.0.5.dist-info/entry_points.txt
lb_dev-0.0.5.dist-info/top_level.txt
lb_dev-0.0.5.dist-info/RECORD
